whitespace_asm/__init__.py
whitespace_asm/asm.py
whitespace_asm/py.typed
whitespace_asm-1.0.1.dist-info/LICENSE
whitespace_asm-1.0.1.dist-info/METADATA
whitespace_asm-1.0.1.dist-info/WHEEL
whitespace_asm-1.0.1.dist-info/entry_points.txt
whitespace_asm-1.0.1.dist-info/RECORD
