Metadata-Version: 2.1
Name: whitespace-asm
Version: 1.0.1
Summary: Assembler for the Whitespace Programming Language
Home-page: https://github.com/rzuckerm/whitespace-asm
License: LICENSE
Author: rzuckerm
Requires-Python: >=3.10,<4.0
Classifier: Development Status :: 3 - Alpha
Classifier: License :: OSI Approved :: MIT License
Classifier: License :: Other/Proprietary License
Classifier: Operating System :: OS Independent
Classifier: Programming Language :: Python :: 3
Classifier: Programming Language :: Python :: 3.10
Classifier: Programming Language :: Python :: 3.11
Classifier: Programming Language :: Python :: 3.12
Project-URL: Bug Tracker, https://github.com/rzuckerm/whitespace-asm/issues
